{"baking":[{"state":"Vermont","popularity":100},{"state":"Maine","popularity":88},{"state":"Washington","popularity":83},{"state":"Montana","popularity":83},{"state":"Alaska","popularity":83},{"state":"Oregon","popularity":82},{"state":"New Hampshire","popularity":81},{"state":"Idaho","popularity":75},{"state":"Connecticut","popularity":74},{"state":"Wisconsin","popularity":73},{"state":"Colorado","popularity":73},{"state":"Minnesota","popularity":73},{"state":"North Dakota","popularity":73},{"state":"Massachusetts","popularity":72},{"state":"Utah","popularity":72},{"state":"South Dakota","popularity":71},{"state":"Hawaii","popularity":70},{"state":"Wyoming","popularity":68},{"state":"Michigan","popularity":67},{"state":"Nebraska","popularity":67},{"state":"Rhode Island","popularity":67},{"state":"Kansas","popularity":66},{"state":"Indiana","popularity":66},{"state":"West Virginia","popularity":66},{"state":"Pennsylvania","popularity":66},{"state":"Iowa","popularity":66},{"state":"New Mexico","popularity":66},{"state":"Virginia","popularity":66},{"state":"Illinois","popularity":65},{"state":"Ohio","popularity":65},{"state":"Arkansas","popularity":64},{"state":"Missouri","popularity":64},{"state":"California","popularity":64},{"state":"Delaware","popularity":64},{"state":"Maryland","popularity":63},{"state":"New York","popularity":63},{"state":"Oklahoma","popularity":63},{"state":"Arizona","popularity":62},{"state":"New Jersey","popularity":61},{"state":"Kentucky","popularity":61},{"state":"North Carolina","popularity":61},{"state":"District of Columbia","popularity":60},{"state":"South Carolina","popularity":60},{"state":"Nevada","popularity":58},{"state":"Tennessee","popularity":58},{"state":"Alabama","popularity":57},{"state":"Georgia","popularity":57},{"state":"Mississippi","popularity":57},{"state":"Louisiana","popularity":55},{"state":"Texas","popularity":55},{"state":"Florida","popularity":53}]}